varconv/__init__.py
varconv/variants.py
varconv-0.1.2.dist-info/METADATA
varconv-0.1.2.dist-info/WHEEL
varconv-0.1.2.dist-info/RECORD
